bdrxml/__init__.py
bdrxml/darwincore.py
bdrxml/foxml.py
bdrxml/irMetadata.py
bdrxml/mets.py
bdrxml/mods.py
bdrxml/rdfns.py
bdrxml/rels.py
bdrxml/rights.py
bdrxml/schemas/dc.xsd
bdrxml/schemas/dcmitype.xsd
bdrxml/schemas/dcterms.xsd
bdrxml/schemas/mods-3-7.xsd
bdrxml/schemas/tdwg_basetypes.xsd
bdrxml/schemas/tdwg_dwc_extensions.xsd
bdrxml/schemas/tdwg_dwc_simple.xsd
bdrxml/schemas/tdwg_dwcterms.xsd
bdrxml/schemas/xlink.xsd
bdrxml/schemas/xml.xsd
test/__init__.py
test/darwincore_test.py
test/foxml_test.py
test/irMetadata_test.py
test/mets_test.py
test/mods_test.py
test/rels_test.py
test/rights_test.py
bdrxml-1.4.dist-info/LICENSE
bdrxml-1.4.dist-info/METADATA
bdrxml-1.4.dist-info/WHEEL
bdrxml-1.4.dist-info/top_level.txt
bdrxml-1.4.dist-info/RECORD
