Metadata-Version: 2.1
Name: bdrxml
Version: 1.4
Summary: UNKNOWN
Home-page: https://github.com/Brown-University-Library/bdrxml
Author: Brown University Library
Author-email: bdr@brown.edu
License: UNKNOWN
Platform: UNKNOWN
Classifier: Programming Language :: Python :: 3
Classifier: License :: OSI Approved :: MIT License
Classifier: Operating System :: OS Independent
License-File: LICENSE
Requires-Dist: eulxml (==1.1.3)
Requires-Dist: ply (==3.8)
Requires-Dist: rdflib
